{"_links":{"self":[{"href":"/feeds/areaofinteresttypes"}]},"_embedded":{"nice.publications:area-of-interest-type-list":{"_links":{"self":[{}]},"_embedded":{"nice.publications:area-of-interest-type":[{"_links":{"self":[{}]},"ETag":null,"LastModified":"2021-02-23T00:00:00","Enabled":true,"Name":"Antimicrobial prescribing","PluralName":"Antimicrobial prescribing","IdentifierPrefix":"AMP"},{"_links":{"self":[{}]},"ETag":null,"LastModified":"2021-02-23T00:00:00","Enabled":true,"Name":"Covid-19","PluralName":"Covid-19","IdentifierPrefix":"COV"}]},"ETag":null}},"ETag":null,"LastModified":"2021-02-23T00:00:00"}